tap_betterstack/__init__.py
tap_betterstack/__main__.py
tap_betterstack/client.py
tap_betterstack/tap.py
tap_betterstack/streams/__init__.py
tap_betterstack/streams/uptime.py
tap_betterstack-0.3.2.dist-info/METADATA
tap_betterstack-0.3.2.dist-info/WHEEL
tap_betterstack-0.3.2.dist-info/entry_points.txt
tap_betterstack-0.3.2.dist-info/licenses/LICENSE
tap_betterstack-0.3.2.dist-info/RECORD
