Metadata-Version: 2.4
Name: tap-betterstack
Version: 0.3.2
Summary: Singer tap for Better Stack, built with the Meltano SDK for Singer Taps.
Project-URL: Documentation, https://github.com/reservoir-data/tap-betterstack#readme
Project-URL: Homepage, https://github.com/reservoir-data/tap-betterstack
Project-URL: Repository, https://github.com/reservoir-data/tap-betterstack
Author-email: Edgar Ramírez-Mondragón <edgarrm358@gmail.com>
License-Expression: Apache-2.0
License-File: LICENSE
Keywords: Better Stack,ELT,singer.io
Classifier: License :: OSI Approved :: Apache Software License
Classifier: Programming Language :: Python :: 3 :: Only
Classifier: Programming Language :: Python :: 3.11
Classifier: Programming Language :: Python :: 3.12
Classifier: Programming Language :: Python :: 3.13
Classifier: Programming Language :: Python :: 3.14
Requires-Python: >=3.11
Requires-Dist: singer-sdk~=0.51.0
Requires-Dist: typing-extensions>=4.15; python_full_version < '3.12'
